kfsdutils/__init__.py
kfsdutils/asgi.py
kfsdutils/settings.py
kfsdutils/urls.py
kfsdutils/wsgi.py
kfsdutils/apps/__init__.py
kfsdutils/apps/core/__init__.py
kfsdutils/apps/core/apps.py
kfsdutils/apps/core/base.py
kfsdutils/apps/core/configuration.py
kfsdutils/apps/core/logger.py
kfsdutils/apps/core/singleton.py
kfsdutils/apps/core/utils.py
kfsdutils/apps/core/yaml.py
kfsdutils/apps/docs/__init__.py
kfsdutils/apps/docs/apps.py
kfsdutils/apps/docs/templates/__init__.py
kfsdutils/apps/docs/templates/browser.html
kfsdutils/apps/docs/templates/skeleton.html
kfsdutils/apps/docs/tests/__init__.py
kfsdutils/apps/docs/tests/test_apibrowserview.py
kfsdutils/apps/docs/views/__init__.py
kfsdutils/apps/docs/views/apibrowser.py
kfsdutils/apps/endpoints/__init__.py
kfsdutils/apps/endpoints/apps.py
kfsdutils/apps/endpoints/exceptions.py
kfsdutils/apps/endpoints/urls.py
kfsdutils/apps/endpoints/handlers/__init__.py
kfsdutils/apps/endpoints/handlers/core/__init__.py
kfsdutils/apps/endpoints/handlers/core/apikeyuser.py
kfsdutils/apps/endpoints/handlers/core/basehandler.py
kfsdutils/apps/endpoints/middleware/__init__.py
kfsdutils/apps/endpoints/middleware/be_auth.py
kfsdutils/apps/endpoints/renderers/__init__.py
kfsdutils/apps/endpoints/renderers/kubefacetsjson.py
kfsdutils/apps/endpoints/renderers/kubefacetstext.py
kfsdutils/apps/endpoints/renderers/kubefacetsyaml.py
kfsdutils/apps/endpoints/serializers/__init__.py
kfsdutils/apps/endpoints/serializers/base.py
kfsdutils/apps/endpoints/serializers/basemodel.py
kfsdutils/apps/endpoints/tests/__init__.py
kfsdutils/apps/endpoints/tests/endpoints_test_handler.py
kfsdutils/apps/endpoints/views/__init__.py
kfsdutils/apps/endpoints/views/baseview.py
kfsdutils/apps/frontend/__init__.py
kfsdutils/apps/frontend/apps.py
kfsdutils/apps/frontend/exceptions.py
kfsdutils/apps/frontend/handlers/__init__.py
kfsdutils/apps/frontend/handlers/apiclient.py
kfsdutils/apps/frontend/handlers/login.py
kfsdutils/apps/frontend/handlers/tokenuser.py
kfsdutils-0.0.92.dist-info/LICENSE
kfsdutils-0.0.92.dist-info/METADATA
kfsdutils-0.0.92.dist-info/WHEEL
kfsdutils-0.0.92.dist-info/top_level.txt
kfsdutils-0.0.92.dist-info/RECORD
