Metadata-Version: 2.1
Name: kfsdutils
Version: 0.0.92
Summary: Sample Pkg
Author: nathangokul
Author-email: nathangokul111@gmail.com
License-File: LICENSE
Requires-Dist: netifaces
Requires-Dist: PyYAML
Requires-Dist: inflect
Requires-Dist: requests
